{"file_name": "C:\\Users\\Dell\\Desktop\\Tracker\\reporting.py", "time_spent": 1.1746809482574463, "change_type": "Other", "change_size": 63, "change_summary": {"additions": 0, "deletions": 60, "modifications": 0, "details": {"added_lines": [], "deleted_lines": [{"line_number": 3, "content": "import pandas as pd"}, {"line_number": 4, "content": "from data_storage import load_tracking_data"}, {"line_number": 5, "content": ""}, {"line_number": 6, "content": "def generate_report(file_path='tracking_data.json'):"}, {"line_number": 7, "content": "print(\"Generating detailed report...\")"}, {"line_number": 8, "content": ""}, {"line_number": 9, "content": "# Load the data"}, {"line_number": 10, "content": "data = load_tracking_data(file_path)"}, {"line_number": 11, "content": "df = pd.DataFrame(data)"}, {"line_number": 12, "content": ""}, {"line_number": 13, "content": "required_columns = ['file_name', 'change_type', 'time_spent', 'change_size', 'change_context', 'change_summary']"}, {"line_number": 14, "content": ""}, {"line_number": 15, "content": "if all(col in df.columns for col in required_columns):"}, {"line_number": 16, "content": "# Group by file name and change type, then sum the time spent"}, {"line_number": 17, "content": "report = df.groupby(['file_name', 'change_type'])[['time_spent', 'change_size']].sum().reset_index()"}, {"line_number": 18, "content": ""}, {"line_number": 19, "content": "print(\"\\nDetailed Report:\")"}, {"line_number": 20, "content": "print(report)"}, {"line_number": 21, "content": ""}, {"line_number": 22, "content": "# Additional insights: total time spent per file and overall time spent"}, {"line_number": 23, "content": "total_time_per_file = df.groupby('file_name').agg({"}, {"line_number": 24, "content": "'time_spent': 'sum',"}, {"line_number": 25, "content": "'change_size': 'sum'"}, {"line_number": 26, "content": "}).reset_index()"}, {"line_number": 27, "content": ""}, {"line_number": 28, "content": "print(\"\\nTotal Time Spent and Change Size Per File:\")"}, {"line_number": 29, "content": "print(total_time_per_file)"}, {"line_number": 30, "content": ""}, {"line_number": 31, "content": "overall_time_spent = df['time_spent'].sum()"}, {"line_number": 32, "content": "overall_change_size = df['change_size'].sum()"}, {"line_number": 33, "content": ""}, {"line_number": 34, "content": "print(f\"\\nOverall Time Spent on All Files: {overall_time_spent:.2f} seconds\")"}, {"line_number": 35, "content": "print(f\"Overall Change Size across All Files: {overall_change_size} lines\")"}, {"line_number": 36, "content": ""}, {"line_number": 37, "content": "# Contextual analysis"}, {"line_number": 38, "content": "print(\"\\nContextual Information for Each File:\")"}, {"line_number": 39, "content": "for file_name, group in df.groupby('file_name'):"}, {"line_number": 40, "content": "print(f\"\\nFile: {file_name}\")"}, {"line_number": 41, "content": "for index, row in group.iterrows():"}, {"line_number": 42, "content": "print(f\"  - Change Type: {row['change_type']}\")"}, {"line_number": 43, "content": "print(f\"  - Time Spent: {row['time_spent']:.2f} seconds\")"}, {"line_number": 44, "content": "print(f\"  - Change Size: {row['change_size']} lines\")"}, {"line_number": 45, "content": "if isinstance(row['change_summary'], dict):"}, {"line_number": 46, "content": "print(f\"  - Summary: Additions: {row['change_summary']['additions']}, \""}, {"line_number": 47, "content": "f\"Deletions: {row['change_summary']['deletions']}, \""}, {"line_number": 48, "content": "f\"Modifications: {row['change_summary']['modifications']}\")"}, {"line_number": 49, "content": "if isinstance(row['change_context'], list):"}, {"line_number": 50, "content": "for context in row['change_context']:"}, {"line_number": 51, "content": "print(f\"    - {context['type']} '{context['name']}' from line {context['start_line']} to {context['end_line']}\")"}, {"line_number": 52, "content": ""}, {"line_number": 53, "content": "else:"}, {"line_number": 54, "content": "print(\"One or more required columns not found in data.\")"}, {"line_number": 55, "content": "print(\"Available columns:\", df.columns)"}, {"line_number": 56, "content": "print(\"Data preview:\")"}, {"line_number": 57, "content": "print(df.head())"}, {"line_number": 58, "content": ""}, {"line_number": 59, "content": "# Example usage"}, {"line_number": 60, "content": "if __name__ == \"__main__\":"}, {"line_number": 61, "content": "generate_report('tracking_data.json')"}, {"line_number": 62, "content": "print()"}], "modified_lines": []}}, "change_context": [{"type": "Function", "name": "generate_report", "start_line": 4, "end_line": 13}]}
{"file_name": "C:\\Users\\Dell\\Desktop\\Tracker\\reporting.py", "time_spent": 0.04552769660949707, "change_type": "Other", "change_size": 63, "change_summary": {"additions": 60, "deletions": 0, "modifications": 0, "details": {"added_lines": [{"line_number": 3, "content": "import pandas as pd"}, {"line_number": 4, "content": "from data_storage import load_tracking_data"}, {"line_number": 5, "content": ""}, {"line_number": 6, "content": "def generate_report(file_path='tracking_data.json'):"}, {"line_number": 7, "content": "print(\"Generating detailed report...\")"}, {"line_number": 8, "content": ""}, {"line_number": 9, "content": "# Load the data"}, {"line_number": 10, "content": "data = load_tracking_data(file_path)"}, {"line_number": 11, "content": "df = pd.DataFrame(data)"}, {"line_number": 12, "content": ""}, {"line_number": 13, "content": "required_columns = ['file_name', 'change_type', 'time_spent', 'change_size', 'change_context', 'change_summary']"}, {"line_number": 14, "content": ""}, {"line_number": 15, "content": "if all(col in df.columns for col in required_columns):"}, {"line_number": 16, "content": "# Group by file name and change type, then sum the time spent"}, {"line_number": 17, "content": "report = df.groupby(['file_name', 'change_type'])[['time_spent', 'change_size']].sum().reset_index()"}, {"line_number": 18, "content": ""}, {"line_number": 19, "content": "print(\"\\nDetailed Report:\")"}, {"line_number": 20, "content": "print(report)"}, {"line_number": 21, "content": ""}, {"line_number": 22, "content": "# Additional insights: total time spent per file and overall time spent"}, {"line_number": 23, "content": "total_time_per_file = df.groupby('file_name').agg({"}, {"line_number": 24, "content": "'time_spent': 'sum',"}, {"line_number": 25, "content": "'change_size': 'sum'"}, {"line_number": 26, "content": "}).reset_index()"}, {"line_number": 27, "content": ""}, {"line_number": 28, "content": "print(\"\\nTotal Time Spent and Change Size Per File:\")"}, {"line_number": 29, "content": "print(total_time_per_file)"}, {"line_number": 30, "content": ""}, {"line_number": 31, "content": "overall_time_spent = df['time_spent'].sum()"}, {"line_number": 32, "content": "overall_change_size = df['change_size'].sum()"}, {"line_number": 33, "content": ""}, {"line_number": 34, "content": "print(f\"\\nOverall Time Spent on All Files: {overall_time_spent:.2f} seconds\")"}, {"line_number": 35, "content": "print(f\"Overall Change Size across All Files: {overall_change_size} lines\")"}, {"line_number": 36, "content": ""}, {"line_number": 37, "content": "# Contextual analysis"}, {"line_number": 38, "content": "print(\"\\nContextual Information for Each File:\")"}, {"line_number": 39, "content": "for file_name, group in df.groupby('file_name'):"}, {"line_number": 40, "content": "print(f\"\\nFile: {file_name}\")"}, {"line_number": 41, "content": "for index, row in group.iterrows():"}, {"line_number": 42, "content": "print(f\"  - Change Type: {row['change_type']}\")"}, {"line_number": 43, "content": "print(f\"  - Time Spent: {row['time_spent']:.2f} seconds\")"}, {"line_number": 44, "content": "print(f\"  - Change Size: {row['change_size']} lines\")"}, {"line_number": 45, "content": "if isinstance(row['change_summary'], dict):"}, {"line_number": 46, "content": "print(f\"  - Summary: Additions: {row['change_summary']['additions']}, \""}, {"line_number": 47, "content": "f\"Deletions: {row['change_summary']['deletions']}, \""}, {"line_number": 48, "content": "f\"Modifications: {row['change_summary']['modifications']}\")"}, {"line_number": 49, "content": "if isinstance(row['change_context'], list):"}, {"line_number": 50, "content": "for context in row['change_context']:"}, {"line_number": 51, "content": "print(f\"    - {context['type']} '{context['name']}' from line {context['start_line']} to {context['end_line']}\")"}, {"line_number": 52, "content": ""}, {"line_number": 53, "content": "else:"}, {"line_number": 54, "content": "print(\"One or more required columns not found in data.\")"}, {"line_number": 55, "content": "print(\"Available columns:\", df.columns)"}, {"line_number": 56, "content": "print(\"Data preview:\")"}, {"line_number": 57, "content": "print(df.head())"}, {"line_number": 58, "content": ""}, {"line_number": 59, "content": "# Example usage"}, {"line_number": 60, "content": "if __name__ == \"__main__\":"}, {"line_number": 61, "content": "generate_report('tracking_data.json')"}, {"line_number": 62, "content": "print(\"\")"}], "deleted_lines": [], "modified_lines": []}}, "change_context": [{"type": "Function", "name": "generate_report", "start_line": 4, "end_line": 13}]}
{"file_name": "C:\\Users\\Dell\\Desktop\\Tracker\\reporting.py", "time_spent": 3.369990348815918, "change_type": "Other", "change_size": 63, "change_summary": {"additions": 0, "deletions": 60, "modifications": 0, "details": {"added_lines": [], "deleted_lines": [{"line_number": 3, "content": "import pandas as pd"}, {"line_number": 4, "content": "from data_storage import load_tracking_data"}, {"line_number": 5, "content": ""}, {"line_number": 6, "content": "def generate_report(file_path='tracking_data.json'):"}, {"line_number": 7, "content": "print(\"Generating detailed report...\")"}, {"line_number": 8, "content": ""}, {"line_number": 9, "content": "# Load the data"}, {"line_number": 10, "content": "data = load_tracking_data(file_path)"}, {"line_number": 11, "content": "df = pd.DataFrame(data)"}, {"line_number": 12, "content": ""}, {"line_number": 13, "content": "required_columns = ['file_name', 'change_type', 'time_spent', 'change_size', 'change_context', 'change_summary']"}, {"line_number": 14, "content": ""}, {"line_number": 15, "content": "if all(col in df.columns for col in required_columns):"}, {"line_number": 16, "content": "# Group by file name and change type, then sum the time spent"}, {"line_number": 17, "content": "report = df.groupby(['file_name', 'change_type'])[['time_spent', 'change_size']].sum().reset_index()"}, {"line_number": 18, "content": ""}, {"line_number": 19, "content": "print(\"\\nDetailed Report:\")"}, {"line_number": 20, "content": "print(report)"}, {"line_number": 21, "content": ""}, {"line_number": 22, "content": "# Additional insights: total time spent per file and overall time spent"}, {"line_number": 23, "content": "total_time_per_file = df.groupby('file_name').agg({"}, {"line_number": 24, "content": "'time_spent': 'sum',"}, {"line_number": 25, "content": "'change_size': 'sum'"}, {"line_number": 26, "content": "}).reset_index()"}, {"line_number": 27, "content": ""}, {"line_number": 28, "content": "print(\"\\nTotal Time Spent and Change Size Per File:\")"}, {"line_number": 29, "content": "print(total_time_per_file)"}, {"line_number": 30, "content": ""}, {"line_number": 31, "content": "overall_time_spent = df['time_spent'].sum()"}, {"line_number": 32, "content": "overall_change_size = df['change_size'].sum()"}, {"line_number": 33, "content": ""}, {"line_number": 34, "content": "print(f\"\\nOverall Time Spent on All Files: {overall_time_spent:.2f} seconds\")"}, {"line_number": 35, "content": "print(f\"Overall Change Size across All Files: {overall_change_size} lines\")"}, {"line_number": 36, "content": ""}, {"line_number": 37, "content": "# Contextual analysis"}, {"line_number": 38, "content": "print(\"\\nContextual Information for Each File:\")"}, {"line_number": 39, "content": "for file_name, group in df.groupby('file_name'):"}, {"line_number": 40, "content": "print(f\"\\nFile: {file_name}\")"}, {"line_number": 41, "content": "for index, row in group.iterrows():"}, {"line_number": 42, "content": "print(f\"  - Change Type: {row['change_type']}\")"}, {"line_number": 43, "content": "print(f\"  - Time Spent: {row['time_spent']:.2f} seconds\")"}, {"line_number": 44, "content": "print(f\"  - Change Size: {row['change_size']} lines\")"}, {"line_number": 45, "content": "if isinstance(row['change_summary'], dict):"}, {"line_number": 46, "content": "print(f\"  - Summary: Additions: {row['change_summary']['additions']}, \""}, {"line_number": 47, "content": "f\"Deletions: {row['change_summary']['deletions']}, \""}, {"line_number": 48, "content": "f\"Modifications: {row['change_summary']['modifications']}\")"}, {"line_number": 49, "content": "if isinstance(row['change_context'], list):"}, {"line_number": 50, "content": "for context in row['change_context']:"}, {"line_number": 51, "content": "print(f\"    - {context['type']} '{context['name']}' from line {context['start_line']} to {context['end_line']}\")"}, {"line_number": 52, "content": ""}, {"line_number": 53, "content": "else:"}, {"line_number": 54, "content": "print(\"One or more required columns not found in data.\")"}, {"line_number": 55, "content": "print(\"Available columns:\", df.columns)"}, {"line_number": 56, "content": "print(\"Data preview:\")"}, {"line_number": 57, "content": "print(df.head())"}, {"line_number": 58, "content": ""}, {"line_number": 59, "content": "# Example usage"}, {"line_number": 60, "content": "if __name__ == \"__main__\":"}, {"line_number": 61, "content": "generate_report('tracking_data.json')"}, {"line_number": 62, "content": "print(\"\")"}], "modified_lines": []}}, "change_context": [{"type": "Function", "name": "generate_report", "start_line": 4, "end_line": 13}]}
{"file_name": "C:\\Users\\Dell\\Desktop\\Tracker\\reporting.py", "time_spent": 0.052304983139038086, "change_type": "Other", "change_size": 63, "change_summary": {"additions": 60, "deletions": 0, "modifications": 0, "details": {"added_lines": [{"line_number": 3, "content": "import pandas as pd"}, {"line_number": 4, "content": "from data_storage import load_tracking_data"}, {"line_number": 5, "content": ""}, {"line_number": 6, "content": "def generate_report(file_path='tracking_data.json'):"}, {"line_number": 7, "content": "print(\"Generating detailed report...\")"}, {"line_number": 8, "content": ""}, {"line_number": 9, "content": "# Load the data"}, {"line_number": 10, "content": "data = load_tracking_data(file_path)"}, {"line_number": 11, "content": "df = pd.DataFrame(data)"}, {"line_number": 12, "content": ""}, {"line_number": 13, "content": "required_columns = ['file_name', 'change_type', 'time_spent', 'change_size', 'change_context', 'change_summary']"}, {"line_number": 14, "content": ""}, {"line_number": 15, "content": "if all(col in df.columns for col in required_columns):"}, {"line_number": 16, "content": "# Group by file name and change type, then sum the time spent"}, {"line_number": 17, "content": "report = df.groupby(['file_name', 'change_type'])[['time_spent', 'change_size']].sum().reset_index()"}, {"line_number": 18, "content": ""}, {"line_number": 19, "content": "print(\"\\nDetailed Report:\")"}, {"line_number": 20, "content": "print(report)"}, {"line_number": 21, "content": ""}, {"line_number": 22, "content": "# Additional insights: total time spent per file and overall time spent"}, {"line_number": 23, "content": "total_time_per_file = df.groupby('file_name').agg({"}, {"line_number": 24, "content": "'time_spent': 'sum',"}, {"line_number": 25, "content": "'change_size': 'sum'"}, {"line_number": 26, "content": "}).reset_index()"}, {"line_number": 27, "content": ""}, {"line_number": 28, "content": "print(\"\\nTotal Time Spent and Change Size Per File:\")"}, {"line_number": 29, "content": "print(total_time_per_file)"}, {"line_number": 30, "content": ""}, {"line_number": 31, "content": "overall_time_spent = df['time_spent'].sum()"}, {"line_number": 32, "content": "overall_change_size = df['change_size'].sum()"}, {"line_number": 33, "content": ""}, {"line_number": 34, "content": "print(f\"\\nOverall Time Spent on All Files: {overall_time_spent:.2f} seconds\")"}, {"line_number": 35, "content": "print(f\"Overall Change Size across All Files: {overall_change_size} lines\")"}, {"line_number": 36, "content": ""}, {"line_number": 37, "content": "# Contextual analysis"}, {"line_number": 38, "content": "print(\"\\nContextual Information for Each File:\")"}, {"line_number": 39, "content": "for file_name, group in df.groupby('file_name'):"}, {"line_number": 40, "content": "print(f\"\\nFile: {file_name}\")"}, {"line_number": 41, "content": "for index, row in group.iterrows():"}, {"line_number": 42, "content": "print(f\"  - Change Type: {row['change_type']}\")"}, {"line_number": 43, "content": "print(f\"  - Time Spent: {row['time_spent']:.2f} seconds\")"}, {"line_number": 44, "content": "print(f\"  - Change Size: {row['change_size']} lines\")"}, {"line_number": 45, "content": "if isinstance(row['change_summary'], dict):"}, {"line_number": 46, "content": "print(f\"  - Summary: Additions: {row['change_summary']['additions']}, \""}, {"line_number": 47, "content": "f\"Deletions: {row['change_summary']['deletions']}, \""}, {"line_number": 48, "content": "f\"Modifications: {row['change_summary']['modifications']}\")"}, {"line_number": 49, "content": "if isinstance(row['change_context'], list):"}, {"line_number": 50, "content": "for context in row['change_context']:"}, {"line_number": 51, "content": "print(f\"    - {context['type']} '{context['name']}' from line {context['start_line']} to {context['end_line']}\")"}, {"line_number": 52, "content": ""}, {"line_number": 53, "content": "else:"}, {"line_number": 54, "content": "print(\"One or more required columns not found in data.\")"}, {"line_number": 55, "content": "print(\"Available columns:\", df.columns)"}, {"line_number": 56, "content": "print(\"Data preview:\")"}, {"line_number": 57, "content": "print(df.head())"}, {"line_number": 58, "content": ""}, {"line_number": 59, "content": "# Example usage"}, {"line_number": 60, "content": "if __name__ == \"__main__\":"}, {"line_number": 61, "content": "generate_report('tracking_data.json')"}, {"line_number": 62, "content": "print(\"Reporting \")"}], "deleted_lines": [], "modified_lines": []}}, "change_context": [{"type": "Function", "name": "generate_report", "start_line": 4, "end_line": 13}]}
{"file_name": "C:\\Users\\Dell\\Desktop\\Tracker\\reporting.py", "time_spent": 1.6189532279968262, "change_type": "Other", "change_size": 63, "change_summary": {"additions": 0, "deletions": 60, "modifications": 0, "details": {"added_lines": [], "deleted_lines": [{"line_number": 3, "content": "import pandas as pd"}, {"line_number": 4, "content": "from data_storage import load_tracking_data"}, {"line_number": 5, "content": ""}, {"line_number": 6, "content": "def generate_report(file_path='tracking_data.json'):"}, {"line_number": 7, "content": "print(\"Generating detailed report...\")"}, {"line_number": 8, "content": ""}, {"line_number": 9, "content": "# Load the data"}, {"line_number": 10, "content": "data = load_tracking_data(file_path)"}, {"line_number": 11, "content": "df = pd.DataFrame(data)"}, {"line_number": 12, "content": ""}, {"line_number": 13, "content": "required_columns = ['file_name', 'change_type', 'time_spent', 'change_size', 'change_context', 'change_summary']"}, {"line_number": 14, "content": ""}, {"line_number": 15, "content": "if all(col in df.columns for col in required_columns):"}, {"line_number": 16, "content": "# Group by file name and change type, then sum the time spent"}, {"line_number": 17, "content": "report = df.groupby(['file_name', 'change_type'])[['time_spent', 'change_size']].sum().reset_index()"}, {"line_number": 18, "content": ""}, {"line_number": 19, "content": "print(\"\\nDetailed Report:\")"}, {"line_number": 20, "content": "print(report)"}, {"line_number": 21, "content": ""}, {"line_number": 22, "content": "# Additional insights: total time spent per file and overall time spent"}, {"line_number": 23, "content": "total_time_per_file = df.groupby('file_name').agg({"}, {"line_number": 24, "content": "'time_spent': 'sum',"}, {"line_number": 25, "content": "'change_size': 'sum'"}, {"line_number": 26, "content": "}).reset_index()"}, {"line_number": 27, "content": ""}, {"line_number": 28, "content": "print(\"\\nTotal Time Spent and Change Size Per File:\")"}, {"line_number": 29, "content": "print(total_time_per_file)"}, {"line_number": 30, "content": ""}, {"line_number": 31, "content": "overall_time_spent = df['time_spent'].sum()"}, {"line_number": 32, "content": "overall_change_size = df['change_size'].sum()"}, {"line_number": 33, "content": ""}, {"line_number": 34, "content": "print(f\"\\nOverall Time Spent on All Files: {overall_time_spent:.2f} seconds\")"}, {"line_number": 35, "content": "print(f\"Overall Change Size across All Files: {overall_change_size} lines\")"}, {"line_number": 36, "content": ""}, {"line_number": 37, "content": "# Contextual analysis"}, {"line_number": 38, "content": "print(\"\\nContextual Information for Each File:\")"}, {"line_number": 39, "content": "for file_name, group in df.groupby('file_name'):"}, {"line_number": 40, "content": "print(f\"\\nFile: {file_name}\")"}, {"line_number": 41, "content": "for index, row in group.iterrows():"}, {"line_number": 42, "content": "print(f\"  - Change Type: {row['change_type']}\")"}, {"line_number": 43, "content": "print(f\"  - Time Spent: {row['time_spent']:.2f} seconds\")"}, {"line_number": 44, "content": "print(f\"  - Change Size: {row['change_size']} lines\")"}, {"line_number": 45, "content": "if isinstance(row['change_summary'], dict):"}, {"line_number": 46, "content": "print(f\"  - Summary: Additions: {row['change_summary']['additions']}, \""}, {"line_number": 47, "content": "f\"Deletions: {row['change_summary']['deletions']}, \""}, {"line_number": 48, "content": "f\"Modifications: {row['change_summary']['modifications']}\")"}, {"line_number": 49, "content": "if isinstance(row['change_context'], list):"}, {"line_number": 50, "content": "for context in row['change_context']:"}, {"line_number": 51, "content": "print(f\"    - {context['type']} '{context['name']}' from line {context['start_line']} to {context['end_line']}\")"}, {"line_number": 52, "content": ""}, {"line_number": 53, "content": "else:"}, {"line_number": 54, "content": "print(\"One or more required columns not found in data.\")"}, {"line_number": 55, "content": "print(\"Available columns:\", df.columns)"}, {"line_number": 56, "content": "print(\"Data preview:\")"}, {"line_number": 57, "content": "print(df.head())"}, {"line_number": 58, "content": ""}, {"line_number": 59, "content": "# Example usage"}, {"line_number": 60, "content": "if __name__ == \"__main__\":"}, {"line_number": 61, "content": "generate_report('tracking_data.json')"}, {"line_number": 62, "content": "print(\"Reporting \")"}], "modified_lines": []}}, "change_context": [{"type": "Function", "name": "generate_report", "start_line": 4, "end_line": 13}]}
{"file_name": "C:\\Users\\Dell\\Desktop\\Tracker\\reporting.py", "time_spent": 0.005993366241455078, "change_type": "Other", "change_size": 63, "change_summary": {"additions": 60, "deletions": 0, "modifications": 0, "details": {"added_lines": [{"line_number": 3, "content": "import pandas as pd"}, {"line_number": 4, "content": "from data_storage import load_tracking_data"}, {"line_number": 5, "content": ""}, {"line_number": 6, "content": "def generate_report(file_path='tracking_data.json'):"}, {"line_number": 7, "content": "print(\"Generating detailed report...\")"}, {"line_number": 8, "content": ""}, {"line_number": 9, "content": "# Load the data"}, {"line_number": 10, "content": "data = load_tracking_data(file_path)"}, {"line_number": 11, "content": "df = pd.DataFrame(data)"}, {"line_number": 12, "content": ""}, {"line_number": 13, "content": "required_columns = ['file_name', 'change_type', 'time_spent', 'change_size', 'change_context', 'change_summary']"}, {"line_number": 14, "content": ""}, {"line_number": 15, "content": "if all(col in df.columns for col in required_columns):"}, {"line_number": 16, "content": "# Group by file name and change type, then sum the time spent"}, {"line_number": 17, "content": "report = df.groupby(['file_name', 'change_type'])[['time_spent', 'change_size']].sum().reset_index()"}, {"line_number": 18, "content": ""}, {"line_number": 19, "content": "print(\"\\nDetailed Report:\")"}, {"line_number": 20, "content": "print(report)"}, {"line_number": 21, "content": ""}, {"line_number": 22, "content": "# Additional insights: total time spent per file and overall time spent"}, {"line_number": 23, "content": "total_time_per_file = df.groupby('file_name').agg({"}, {"line_number": 24, "content": "'time_spent': 'sum',"}, {"line_number": 25, "content": "'change_size': 'sum'"}, {"line_number": 26, "content": "}).reset_index()"}, {"line_number": 27, "content": ""}, {"line_number": 28, "content": "print(\"\\nTotal Time Spent and Change Size Per File:\")"}, {"line_number": 29, "content": "print(total_time_per_file)"}, {"line_number": 30, "content": ""}, {"line_number": 31, "content": "overall_time_spent = df['time_spent'].sum()"}, {"line_number": 32, "content": "overall_change_size = df['change_size'].sum()"}, {"line_number": 33, "content": ""}, {"line_number": 34, "content": "print(f\"\\nOverall Time Spent on All Files: {overall_time_spent:.2f} seconds\")"}, {"line_number": 35, "content": "print(f\"Overall Change Size across All Files: {overall_change_size} lines\")"}, {"line_number": 36, "content": ""}, {"line_number": 37, "content": "# Contextual analysis"}, {"line_number": 38, "content": "print(\"\\nContextual Information for Each File:\")"}, {"line_number": 39, "content": "for file_name, group in df.groupby('file_name'):"}, {"line_number": 40, "content": "print(f\"\\nFile: {file_name}\")"}, {"line_number": 41, "content": "for index, row in group.iterrows():"}, {"line_number": 42, "content": "print(f\"  - Change Type: {row['change_type']}\")"}, {"line_number": 43, "content": "print(f\"  - Time Spent: {row['time_spent']:.2f} seconds\")"}, {"line_number": 44, "content": "print(f\"  - Change Size: {row['change_size']} lines\")"}, {"line_number": 45, "content": "if isinstance(row['change_summary'], dict):"}, {"line_number": 46, "content": "print(f\"  - Summary: Additions: {row['change_summary']['additions']}, \""}, {"line_number": 47, "content": "f\"Deletions: {row['change_summary']['deletions']}, \""}, {"line_number": 48, "content": "f\"Modifications: {row['change_summary']['modifications']}\")"}, {"line_number": 49, "content": "if isinstance(row['change_context'], list):"}, {"line_number": 50, "content": "for context in row['change_context']:"}, {"line_number": 51, "content": "print(f\"    - {context['type']} '{context['name']}' from line {context['start_line']} to {context['end_line']}\")"}, {"line_number": 52, "content": ""}, {"line_number": 53, "content": "else:"}, {"line_number": 54, "content": "print(\"One or more required columns not found in data.\")"}, {"line_number": 55, "content": "print(\"Available columns:\", df.columns)"}, {"line_number": 56, "content": "print(\"Data preview:\")"}, {"line_number": 57, "content": "print(df.head())"}, {"line_number": 58, "content": ""}, {"line_number": 59, "content": "# Example usage"}, {"line_number": 60, "content": "if __name__ == \"__main__\":"}, {"line_number": 61, "content": "generate_report('tracking_data.json')"}, {"line_number": 62, "content": "print(\"Reporting File\")"}], "deleted_lines": [], "modified_lines": []}}, "change_context": [{"type": "Function", "name": "generate_report", "start_line": 4, "end_line": 13}]}
